PDFFiller/__init__.py
PDFFiller/exceptions.py
PDFFiller/attributes/__init__.py
PDFFiller/attributes/color.py
PDFFiller/attributes/dimension.py
PDFFiller/attributes/font.py
PDFFiller/attributes/position.py
PDFFiller/components/__init__.py
PDFFiller/components/check_mark/__init__.py
PDFFiller/components/check_mark/check_mark.py
PDFFiller/components/check_mark/check_mark_theme.py
PDFFiller/components/check_mark/check_mark_value.py
PDFFiller/components/debug_box/__init__.py
PDFFiller/components/debug_box/debug_box.py
PDFFiller/components/debug_box/debug_box_theme.py
PDFFiller/components/image_box/__init__.py
PDFFiller/components/image_box/image_box.py
PDFFiller/components/image_box/image_box_theme.py
PDFFiller/components/image_box/image_box_value.py
PDFFiller/components/signing_area/__init__.py
PDFFiller/components/signing_area/signing_area.py
PDFFiller/components/signing_area/signing_area_theme.py
PDFFiller/components/signing_area/signing_area_value.py
PDFFiller/components/text_field/__init__.py
PDFFiller/components/text_field/text_field.py
PDFFiller/components/text_field/text_field_theme.py
PDFFiller/components/text_field/text_field_value.py
PDFFiller/constants/__init__.py
PDFFiller/constants/enums.py
PDFFiller/constants/settings.py
PDFFiller/core/__init__.py
PDFFiller/core/pdf_filler.py
PDFFiller/core/template.py
PDFFiller/core/build_service/__init__.py
PDFFiller/core/build_service/factory.py
PDFFiller/core/build_service/fitz_build_service/__init__.py
PDFFiller/core/build_service/fitz_build_service/build_service.py
PDFFiller/core/build_service/fitz_build_service/check_mark_builder.py
PDFFiller/core/build_service/fitz_build_service/debug_box_builder.py
PDFFiller/core/build_service/fitz_build_service/image_box_builder.py
PDFFiller/core/build_service/fitz_build_service/signing_area_builder.py
PDFFiller/core/build_service/fitz_build_service/text_field_builder.py
PDFFiller/core/export_service/__init__.py
PDFFiller/core/export_service/factory.py
PDFFiller-0.2.4.dist-info/LICENSE.md
PDFFiller-0.2.4.dist-info/METADATA
PDFFiller-0.2.4.dist-info/WHEEL
PDFFiller-0.2.4.dist-info/top_level.txt
PDFFiller-0.2.4.dist-info/RECORD
