Metadata-Version: 2.1
Name: PDFFiller
Version: 0.2.4
Summary: Simple library to fill PDF documents
Home-page: https://github.com/Moussawi7/pdf-filler
Author: Ali Moussawi
Author-email: moussawidev@gmail.com
Classifier: Programming Language :: Python :: 3
Classifier: License :: OSI Approved :: MIT License
Classifier: Operating System :: OS Independent
Requires-Python: >=3.9
License-File: LICENSE.md
Requires-Dist: PyMuPDF >=1.23.7
